.gitignore
MANIFEST.in
README.txt
bootstrap.py
buildout.cfg
setup.py
collective/__init__.py
collective.portlet.itemview.egg-info/PKG-INFO
collective.portlet.itemview.egg-info/SOURCES.txt
collective.portlet.itemview.egg-info/dependency_links.txt
collective.portlet.itemview.egg-info/entry_points.txt
collective.portlet.itemview.egg-info/namespace_packages.txt
collective.portlet.itemview.egg-info/not-zip-safe
collective.portlet.itemview.egg-info/requires.txt
collective.portlet.itemview.egg-info/top_level.txt
collective/portlet/__init__.py
collective/portlet/itemview/__init__.py
collective/portlet/itemview/configure.zcml
collective/portlet/itemview/i18n.py
collective/portlet/itemview/itemview_portlet.pt
collective/portlet/itemview/itemview_portlet.py
collective/portlet/itemview/itemview_portlet_event.pt
collective/portlet/itemview/itemview_portlet_file.pt
collective/portlet/itemview/itemview_portlet_image.pt
collective/portlet/itemview/itemview_portlet_topic.pt
collective/portlet/itemview/portlet.py
collective/portlet/itemview/rebuild_i18n.sh
collective/portlet/itemview/tests.py
collective/portlet/itemview/vocabulary.py
collective/portlet/itemview/locales/collective.portlet.itemview.pot
collective/portlet/itemview/locales/fr/LC_MESSAGES/collective.portlet.itemview.po
collective/portlet/itemview/profiles/default/metadata.xml
collective/portlet/itemview/profiles/default/portlets.xml
docs/HISTORY.txt
docs/INSTALL.txt
docs/LICENSE.GPL
docs/LICENSE.txt