Metadata-Version: 1.0
Name: collective.portlet.itemview
Version: 1.4
Summary: A portlet where you can select one item, and render it with a view
Home-page: https://github.com/collective/collective.portlet.itemview
Author: JeanMichel FRANCOIS aka toutpt
Author-email: jeanmichel.francois@makina-corpus.com
License: GPL
Keywords: plone portlet
Platform: UNKNOWN
Classifier: Environment :: Web Environment
Classifier: License :: OSI Approved :: GNU General Public License (GPL)
Classifier: Operating System :: OS Independent
Classifier: Framework :: Plone
Classifier: Framework :: Plone :: 4.0
Classifier: Framework :: Plone :: 4.1
Classifier: Framework :: Plone :: 4.2
Classifier: Programming Language :: Python
